easyRedisCache/__init__.py
easyRedisCache/test.py
easyRedisCache-0.151.dist-info/DESCRIPTION.rst
easyRedisCache-0.151.dist-info/METADATA
easyRedisCache-0.151.dist-info/RECORD
easyRedisCache-0.151.dist-info/WHEEL
easyRedisCache-0.151.dist-info/dependency_links.txt
easyRedisCache-0.151.dist-info/metadata.json
easyRedisCache-0.151.dist-info/top_level.txt
