Metadata-Version: 2.0
Name: easyRedisCache
Version: 0.151
Summary: Easy lock secured cache for redis
Home-page: https://github.com/InfinityMod/easyRedisCache
Author: David Ziegler
Author-email: webmaster@SpreadPost.de
License: BSD
Keywords: cache,lock,redis,easy
Platform: UNKNOWN
Requires-Dist: redis
Requires-Dist: redisSherlock
